simple_data_loader/__init__.py
simple_data_loader/simple_data_loader.py
simple_data_loader-1.0.5.dist-info/licenses/LICENSE
simple_data_loader-1.0.5.dist-info/METADATA
simple_data_loader-1.0.5.dist-info/WHEEL
simple_data_loader-1.0.5.dist-info/top_level.txt
simple_data_loader-1.0.5.dist-info/RECORD
