Metadata-Version: 2.4
Name: simple-data-loader
Version: 1.0.5
Summary: A simple Python package for loading data from CSV and XLSX files
Author-email: Zhongjie Shen <askme@zshen.ca>
Maintainer-email: Zhongjie Shen <askme@zshen.ca>
License: MIT
Project-URL: Homepage, https://github.com/shenzj1994/simple_data_loader
Project-URL: Repository, https://github.com/shenzj1994/simple_data_loader
Project-URL: Issues, https://github.com/shenzj1994/simple_data_loader/issues
Project-URL: Documentation, https://github.com/shenzj1994/simple_data_loader#readme
Keywords: data loading,csv,xlsx,pandas,data analysis
Classifier: Development Status :: 4 - Beta
Classifier: Intended Audience :: Developers
Classifier: License :: OSI Approved :: MIT License
Classifier: Operating System :: OS Independent
Classifier: Programming Language :: Python :: 3
Classifier: Programming Language :: Python :: 3.8
Classifier: Programming Language :: Python :: 3.9
Classifier: Programming Language :: Python :: 3.10
Classifier: Programming Language :: Python :: 3.11
Classifier: Programming Language :: Python :: 3.12
Classifier: Programming Language :: Python :: 3.13
Classifier: Topic :: Software Development :: Libraries :: Python Modules
Classifier: Topic :: Scientific/Engineering :: Information Analysis
Requires-Python: >=3.8
License-File: LICENSE
Requires-Dist: pandas>=1.3.0
Requires-Dist: openpyxl>=3.0.0
Requires-Dist: xlrd>=2.0.0
Provides-Extra: dev
Requires-Dist: pytest>=7.0.0; extra == "dev"
Requires-Dist: pytest-cov>=4.0.0; extra == "dev"
Dynamic: license-file
